twisted_iocpsupport/iocpsupport.pypy39-pp73-win_amd64.pyd
twisted_iocpsupport-25.2.0.dist-info/LICENSE
twisted_iocpsupport-25.2.0.dist-info/METADATA
twisted_iocpsupport-25.2.0.dist-info/WHEEL
twisted_iocpsupport-25.2.0.dist-info/top_level.txt
twisted_iocpsupport-25.2.0.dist-info/RECORD
