Metadata-Version: 2.2
Name: twisted-iocpsupport
Version: 25.2.0
Summary: An extension for use in the twisted I/O Completion Ports reactor.
Home-page: https://github.com/twisted/twisted-iocpsupport
Author: Twisted Matrix Laboratories
Author-email: twisted-python@twistedmatrix.com
Maintainer: Thomas Grainger
Maintainer-email: twisted-iocpsupport@graingert.co.uk
License: MIT
Classifier: Programming Language :: Python :: 3
Classifier: Programming Language :: Python :: 3 :: Only
Classifier: Programming Language :: Python :: 3.8
Classifier: Programming Language :: Python :: 3.9
Classifier: Programming Language :: Python :: 3.10
Classifier: Programming Language :: Python :: 3.11
Classifier: Programming Language :: Python :: 3.12
Classifier: Programming Language :: Python :: 3.13
License-File: LICENSE
